{
  "format_version": "1.13.0",
  "minecraft:biome": {
    "components": {
      "mutated": {},
      "warm": {},
      "minecraft:surface_parameters": {
        "sea_floor_depth": 7,
        "top_material": "minecraft:coal_ore",
        "sea_material": "minecraft:water",
        "mid_material": "minecraft:coal_ore",
        "sea_floor_material": "minecraft:loom",
        "foundation_material": "minecraft:log"
      },
      "beach": {},
      "animal": {},
      "minecraft:overworld_height": {"noise_type": "beach"},
      "overworld": {},
      "minecraft:climate": {
        "snow_accumulation": [
          0,
          0.125
        ],
        "temperature": 0.8,
        "downfall": 0.4
      },
      "monster": {}
    },
    "description": {"identifier": "beach"}
  }
}