{
  "format_version": "1.8.0",
  "minecraft:spawn_rules": {
    "description": {
      "identifier": "minecraft:tropicalfish",
      "population_control": "water_animal"
    },
    "conditions": [
      {
        "minecraft:herd": [
          {
            "min_size": 3,
            "event": "minecraft:become_anenonme",
            "max_size": 5
          },
          {
            "min_size": 3,
            "event": "minecraft:become_black_tang",
            "max_size": 5
          },
          {
            "min_size": 3,
            "event": "minecraft:become_blue_dory",
            "max_size": 5
          },
          {
            "min_size": 3,
            "event": "minecraft:become_butterfly_fish",
            "max_size": 5
          },
          {
            "min_size": 3,
            "event": "minecraft:become_cichlid",
            "max_size": 5
          },
          {
            "min_size": 3,
            "event": "minecraft:become_clownfish",
            "max_size": 5
          },
          {
            "min_size": 3,
            "event": "minecraft:become_cc_betta",
            "max_size": 5
          },
          {
            "min_size": 3,
            "event": "minecraft:become_dog_fish",
            "max_size": 5
          },
          {
            "min_size": 3,
            "event": "minecraft:become_e_red_snapper",
            "max_size": 5
          },
          {
            "min_size": 3,
            "event": "minecraft:become_goat_fish",
            "max_size": 5
          },
          {
            "min_size": 3,
            "event": "minecraft:become_moorish_idol",
            "max_size": 5
          },
          {
            "min_size": 3,
            "event": "minecraft:become_ornate_butterfly",
            "max_size": 5
          },
          {
            "min_size": 3,
            "event": "minecraft:become_parrot_fish",
            "max_size": 5
          },
          {
            "min_size": 3,
            "event": "minecraft:become_queen_angel_fish",
            "max_size": 5
          },
          {
            "min_size": 3,
            "event": "minecraft:become_red_cichlid",
            "max_size": 5
          },
          {
            "min_size": 3,
            "event": "minecraft:become_red_lipped_benny",
            "max_size": 5
          },
          {
            "min_size": 3,
            "event": "minecraft:become_red_snapper",
            "max_size": 5
          },
          {
            "min_size": 3,
            "event": "minecraft:become_threadfin",
            "max_size": 5
          },
          {
            "min_size": 3,
            "event": "minecraft:become_tomato_clown",
            "max_size": 5
          },
          {
            "min_size": 3,
            "event": "minecraft:become_triggerfish",
            "max_size": 5
          },
          {
            "min_size": 3,
            "event": "minecraft:become_yellow_tang",
            "max_size": 5
          },
          {
            "min_size": 3,
            "event": "minecraft:become_yellow_tail_parrot",
            "max_size": 5
          }
        ],
        "minecraft:spawns_underwater": {},
        "minecraft:spawns_on_surface": {},
        "minecraft:weight": {"default": 75},
        "minecraft:density_limit": {"surface": 20},
        "minecraft:biome_filter": [
          {
            "test": "has_biome_tag",
            "value": "ocean",
            "operator": "=="
          },
          {
            "test": "has_biome_tag",
            "value": "warm",
            "operator": "=="
          }
        ],
        "minecraft:distance_filter": {
          "min": 12,
          "max": 32
        }
      },
      {
        "minecraft:herd": {
          "min_size": 1,
          "max_size": 3
        },
        "minecraft:spawns_underwater": {},
        "minecraft:spawns_on_surface": {},
        "minecraft:weight": {"default": 25},
        "minecraft:density_limit": {"surface": 20},
        "minecraft:biome_filter": [
          {
            "test": "has_biome_tag",
            "value": "ocean",
            "operator": "=="
          },
          {
            "test": "has_biome_tag",
            "value": "warm",
            "operator": "=="
          }
        ],
        "minecraft:distance_filter": {
          "min": 12,
          "max": 32
        }
      }
    ]
  }
}